krux/__init__.py
krux/values.py
krux/converters/__init__.py
krux/converters/misc.py
krux/converters/string_related.py
krux/converters/structure.py
krux/functools/__init__.py
krux/functools/cache.py
krux/lodash/__init__.py
krux/lodash/array_funcs.py
krux/lodash/dict_funcs.py
krux/para/__init__.py
krux/para/classes.py
krux/para/exceptions.py
krux/random/__init__.py
krux/random/uuid.py
krux/regex/__init__.py
krux/regex/exceptions.py
krux/regex/grep.py
krux/regex/pattern.py
krux/schema/__init__.py
krux/schema/classes.py
krux/schema/exceptions.py
krux/types/__init__.py
krux/types/check.py
krux/types/null.py
krux/types/singleton.py
krux-0.0.38.dist-info/licenses/LICENSE
tests/__init__.py
tests/test_para.py
tests/test_schema.py
tests/test_simple_pattern.py
tests/test_str2obj.py
tests/test_values.py
krux-0.0.38.dist-info/METADATA
krux-0.0.38.dist-info/WHEEL
krux-0.0.38.dist-info/top_level.txt
krux-0.0.38.dist-info/RECORD
