Metadata-Version: 2.4
Name: krux
Version: 0.0.38
Summary: misc utils
Home-page: https://github.com/claydodo/krux
Author: claydodo and his little friends (xiao huo ban)
Author-email: claydodo@foxmail.com
Classifier: Operating System :: OS Independent
License-File: LICENSE
Dynamic: author
Dynamic: author-email
Dynamic: classifier
Dynamic: home-page
Dynamic: license-file
Dynamic: summary
